lotodice/__init__.py
lotodice/__main__.py
lotodice/browser.py
lotodice/jogo.py
lotodice/mega.py
lotodice/quina.py
lotodice/resultados.py
lotodice-0.1.0.dist-info/LICENSE
lotodice-0.1.0.dist-info/METADATA
lotodice-0.1.0.dist-info/WHEEL
lotodice-0.1.0.dist-info/entry_points.txt
lotodice-0.1.0.dist-info/top_level.txt
lotodice-0.1.0.dist-info/RECORD
