Metadata-Version: 2.1
Name: lotodice
Version: 0.1.0
Summary: lotodice é uma ferramenta em Python para gerar e verificar jogos da Mega Sena e Quina.
Home-page: https://github.com/calebe94/lotodice
Author: Edimar Calebe Castanho
Author-email: contato@calebe.dev.br
License: GPL3+
Project-URL: Bug Tracker, https://github.com/calebe94/lotodice/issues
Classifier: Programming Language :: Python :: 3
Classifier: License :: OSI Approved :: GNU General Public License v3 or later (GPLv3+)
Classifier: Operating System :: POSIX
Requires-Python: >=3.6
License-File: LICENSE
Requires-Dist: selenium
